CHANGES.rst
COPYING.txt
MANIFEST.in
README.rst
setup.py
pyramid_rewrite/__init__.py
pyramid_rewrite.egg-info/PKG-INFO
pyramid_rewrite.egg-info/SOURCES.txt
pyramid_rewrite.egg-info/dependency_links.txt
pyramid_rewrite.egg-info/requires.txt
pyramid_rewrite.egg-info/top_level.txt