Metadata-Version: 1.0
Name: pyramid-rewrite
Version: 0.2
Summary: Small Pyramid extension for rewriting urls
Home-page: https://github.com/bennihepp/pyramid_rewrite
Author: Benjamin Hepp
Author-email: benjamin.hepp@gmail.com
License: BSD
Keywords: pyramid rewrite pylons web
Platform: UNKNOWN
Classifier: Operating System :: OS Independent
Classifier: License :: OSI Approved :: BSD License
Classifier: Programming Language :: Python
Classifier: Development Status :: 4 - Beta
Classifier: Intended Audience :: Developers
Classifier: Framework :: Pylons
Classifier: Topic :: Internet :: WWW/HTTP
Classifier: Topic :: Internet :: WWW/HTTP :: WSGI
Classifier: Topic :: Software Development :: Libraries :: Python Modules
